pyaquifer/__init__.py
pyaquifer/config.py
pyaquifer/main.py
pyaquifer/connectors/__init__.py
pyaquifer/connectors/duckdb.py
pyaquifer/connectors/engine.py
pyaquifer/connectors/glue.py
pyaquifer/connectors/iceberg.py
pyaquifer/connectors/pandas.py
pyaquifer/connectors/polars.py
pyaquifer-0.1.1.dist-info/licenses/LICENSE
pyaquifer-0.1.1.dist-info/METADATA
pyaquifer-0.1.1.dist-info/WHEEL
pyaquifer-0.1.1.dist-info/top_level.txt
pyaquifer-0.1.1.dist-info/RECORD
