Metadata-Version: 2.4
Name: pyaquifer
Version: 0.1.1
Summary: A high-level library to simplify data operations on AWS data lakes.
Requires-Python: >=3.8
License-File: LICENSE
Requires-Dist: pandas
Requires-Dist: pyarrow
Requires-Dist: boto3
Requires-Dist: pyiceberg
Requires-Dist: polars
Requires-Dist: duckdb
Dynamic: license-file
